irc/__init__.py
irc/bot.py
irc/client.py
irc/client_aio.py
irc/connection.py
irc/ctcp.py
irc/dict.py
irc/events.py
irc/features.py
irc/message.py
irc/modes.py
irc/rfc.py
irc/rfc2812.txt
irc/schedule.py
irc/server.py
irc/strings.py
irc/tests/__init__.py
irc/tests/test_bot.py
irc/tests/test_client.py
irc/tests/test_client_aio.py
irc-20.4.3.dist-info/LICENSE
irc-20.4.3.dist-info/METADATA
irc-20.4.3.dist-info/WHEEL
irc-20.4.3.dist-info/top_level.txt
irc-20.4.3.dist-info/RECORD
