Metadata-Version: 2.1
Name: irc
Version: 20.4.3
Summary: IRC (Internet Relay Chat) protocol library for Python
Author-email: "Jason R. Coombs" <jaraco@jaraco.com>
Project-URL: Source, https://github.com/jaraco/irc
Classifier: Development Status :: 5 - Production/Stable
Classifier: Intended Audience :: Developers
Classifier: License :: OSI Approved :: MIT License
Classifier: Programming Language :: Python :: 3
Classifier: Programming Language :: Python :: 3 :: Only
Requires-Python: >=3.8
License-File: LICENSE
Requires-Dist: jaraco.collections
Requires-Dist: jaraco.text >=3.10
Requires-Dist: jaraco.logging
Requires-Dist: jaraco.functools >=1.20
Requires-Dist: jaraco.stream
Requires-Dist: pytz
Requires-Dist: more-itertools
Requires-Dist: tempora >=1.6
Requires-Dist: importlib-metadata ; python_version < "3.8"
Provides-Extra: doc
Requires-Dist: sphinx >=3.5 ; extra == 'doc'
Requires-Dist: jaraco.packaging >=9.3 ; extra == 'doc'
Requires-Dist: rst.linker >=1.9 ; extra == 'doc'
Requires-Dist: furo ; extra == 'doc'
Requires-Dist: sphinx-lint ; extra == 'doc'
Requires-Dist: jaraco.tidelift >=1.4 ; extra == 'doc'
Provides-Extra: test
Requires-Dist: pytest !=8.1.*,>=6 ; extra == 'test'
Requires-Dist: pytest-checkdocs >=2.4 ; extra == 'test'
Requires-Dist: pytest-cov ; extra == 'test'
Requires-Dist: pytest-mypy ; extra == 'test'
Requires-Dist: pytest-enabler >=2.2 ; extra == 'test'
Requires-Dist: pytest-ruff >=0.2.1 ; extra == 'test'
Requires-Dist: pygments ; extra == 'test'
